tephigram/__init__.py
tephigram/parameterisations.py
tephigram/plotter.py
tephigram/profile_integration.py
tephigram-0.2.0.dist-info/METADATA
tephigram-0.2.0.dist-info/RECORD
tephigram-0.2.0.dist-info/WHEEL
tephigram-0.2.0.dist-info/top_level.txt
tephigram_python/__init__.py
tephigram_python/parameterisations.py
tephigram_python/plotter.py
tephigram_python/profile_integration.py
