Metadata-Version: 2.1
Name: tephigram
Version: 0.2.0
Summary: Tephigram plotting and profile integration
Home-page: UNKNOWN
Author: Leif Denby
Author-email: l.c.denby@leeds.ac.uk
License: UNKNOWN
Platform: UNKNOWN
Requires-Dist: attrdict
